sync_git_repos/__init__.py
sync_git_repos/__main__.py
sync_git_repos/hooks.py
sync_git_repos/utils.py
sync_git_repos-0.0.6.dist-info/LICENSE
sync_git_repos-0.0.6.dist-info/METADATA
sync_git_repos-0.0.6.dist-info/WHEEL
sync_git_repos-0.0.6.dist-info/top_level.txt
sync_git_repos-0.0.6.dist-info/RECORD
