Metadata-Version: 2.1
Name: sync-git-repos
Version: 0.0.6
Summary: Command for syncing git repos
Author: Anton Gorinenko
Author-email: anton.gorinenko@gmail.com
Keywords: python,utils,git
Classifier: Programming Language :: Python :: 3.8
Classifier: Operating System :: OS Independent
Requires-Python: >=3.8
License-File: LICENSE
Provides-Extra: test
Requires-Dist: pytest ; extra == 'test'
Requires-Dist: pylint ; extra == 'test'
